eddymc_core/__init__.py
eddymc_core/eddy.py
eddymc_core/mcnp/__init__.py
eddymc_core/mcnp/cells.py
eddymc_core/mcnp/cerberus_logo.py
eddymc_core/mcnp/eddy_mcnp_case.py
eddymc_core/mcnp/mcnp_html_writer.py
eddymc_core/mcnp/particles.py
eddymc_core/mcnp/tallies.py
eddymc_core/scale/__init__.py
eddymc_core/scale/eddy_scale_case.py
eddymc_core/scale/mixtures.py
eddymc_core/scale/scale_html_writer.py
eddymc_core/scale/scale_tallies.py
eddymc_core/static/MCNP_template.html
eddymc_core/static/SCALE_template.html
eddymc_core/static/__init__.py
eddymc_core/static/style.css
eddy_mc_core-0.4.4.dist-info/LICENSE
eddy_mc_core-0.4.4.dist-info/METADATA
eddy_mc_core-0.4.4.dist-info/WHEEL
eddy_mc_core-0.4.4.dist-info/top_level.txt
eddy_mc_core-0.4.4.dist-info/RECORD
