Metadata-Version: 2.1
Name: eddy-mc-core
Version: 0.4.4
Summary: Eddy, the MCNP and SCALE HTML output converter
Home-page: https://github.com/Cerberus-Nuclear/Eddy-Core
Author: Cerberus Nuclear
Author-email: nuclear@cerberusnuclear.com
License: UNKNOWN
Platform: UNKNOWN
Classifier: Programming Language :: Python :: 3
Classifier: License :: OSI Approved :: GNU General Public License v3 or later (GPLv3+)
Classifier: Operating System :: OS Independent
Requires-Python: >=3.6
Requires-Dist: Jinja2
Requires-Dist: importlib-resources
